<?xml version="1.0" encoding="UTF-8" standalone="yes"?>
<Invoice xmlns="urn:oasis:names:specification:ubl:schema:xsd:Invoice-2" xmlns:cbc="urn:oasis:names:specification:ubl:schema:xsd:CommonBasicComponents-2" xmlns:cac="urn:oasis:names:specification:ubl:schema:xsd:CommonAggregateComponents-2" xmlns:ns4="urn:oasis:names:specification:ubl:schema:xsd:CommonExtensionComponents-2" xmlns:xsi="http://www.w3.org/2001/XMLSchema-instance" xsi:schemaLocation="urn:oasis:names:specification:ubl:schema:xsd:Invoice-2 http://docs.oasis-open.org/ubl/os-UBL-2.1/xsd/maindoc/UBL-Invoice-2.1.xsd">
    <cbc:CustomizationID>urn:cen.eu:en16931:2017#compliant#urn:efactura.mfinante.ro:CIUS-RO:1.0.1</cbc:CustomizationID>
    <cbc:ID>6419259574</cbc:ID>
    <cbc:IssueDate>2023-01-23</cbc:IssueDate>
    <cbc:DueDate>2024-03-29</cbc:DueDate>
    <cbc:InvoiceTypeCode>382</cbc:InvoiceTypeCode>
    <cbc:DocumentCurrencyCode>RON</cbc:DocumentCurrencyCode>
    <cbc:TaxCurrencyCode>EUR</cbc:TaxCurrencyCode>
    <cac:InvoicePeriod>
        <cbc:DescriptionCode>2</cbc:DescriptionCode>
    </cac:InvoicePeriod>
    <cac:AccountingSupplierParty>
        <cac:Party>
            <cac:PartyName>
                <cbc:Name>Green-Little</cbc:Name>
            </cac:PartyName>
            <cac:PostalAddress>
                <cbc:StreetName>331 Anna Parks Suite 241</cbc:StreetName>
                <cbc:CityName>Perezhaven</cbc:CityName>
                <cbc:PostalZone>92423</cbc:PostalZone>
                <cbc:CountrySubentity>RO-B</cbc:CountrySubentity>
                <cac:Country>
                    <cbc:IdentificationCode>RO</cbc:IdentificationCode>
                </cac:Country>
            </cac:PostalAddress>
            <cac:PartyTaxScheme>
                <cbc:CompanyID>2216202845</cbc:CompanyID>
                <cac:TaxScheme>
                    <cbc:ID>VAT</cbc:ID>
                </cac:TaxScheme>
            </cac:PartyTaxScheme>
            <cac:PartyLegalEntity>
                <cbc:RegistrationName>Bass Ltd</cbc:RegistrationName>
            </cac:PartyLegalEntity>
        </cac:Party>
    </cac:AccountingSupplierParty>
    <cac:AccountingCustomerParty>
        <cac:Party>
            <cac:PartyName>
                <cbc:Name>Johnson Inc</cbc:Name>
            </cac:PartyName>
            <cac:PostalAddress>
                <cbc:StreetName>94024 Sabrina Camp Apt. 685</cbc:StreetName>
                <cbc:CityName>Angelaton</cbc:CityName>
                <cbc:PostalZone>61128</cbc:PostalZone>
                <cbc:CountrySubentity>RO-B</cbc:CountrySubentity>
                <cac:Country>
                    <cbc:IdentificationCode>RO</cbc:IdentificationCode>
                </cac:Country>
            </cac:PostalAddress>
            <cac:PartyTaxScheme>
                <cbc:CompanyID>295730846</cbc:CompanyID>
                <cac:TaxScheme>
                    <cbc:ID>VAT</cbc:ID>
                </cac:TaxScheme>
            </cac:PartyTaxScheme>
            <cac:PartyLegalEntity>
                <cbc:RegistrationName>Burke Group</cbc:RegistrationName>
            </cac:PartyLegalEntity>
        </cac:Party>
    </cac:AccountingCustomerParty>
    <cac:Delivery>
        <cac:DeliveryLocation>
            <cac:Address>
                <cbc:StreetName>7896 Elizabeth Cove</cbc:StreetName>
                <cbc:CityName>Olsonmouth</cbc:CityName>
                <cbc:PostalZone>92060</cbc:PostalZone>
                <cbc:CountrySubentity>RO-AB</cbc:CountrySubentity>
                <cac:Country>
                    <cbc:IdentificationCode>RO</cbc:IdentificationCode>
                </cac:Country>
            </cac:Address>
        </cac:DeliveryLocation>
    </cac:Delivery>
    <cac:PaymentMeans>
        <cbc:PaymentMeansCode>20</cbc:PaymentMeansCode>
    </cac:PaymentMeans>
    <cac:TaxTotal>
        <cbc:TaxAmount currencyID="RON">309.82</cbc:TaxAmount>
        <cac:TaxSubtotal>
            <cbc:TaxableAmount currencyID="RON">5442.28</cbc:TaxableAmount>
            <cbc:TaxAmount currencyID="RON">309.82</cbc:TaxAmount>
            <cac:TaxCategory>
                <cbc:ID>E</cbc:ID>
                <cbc:Percent>2.78</cbc:Percent>
                <cbc:TaxExemptionReason>redefine user-centric convergence</cbc:TaxExemptionReason>
                <cac:TaxScheme>
                    <cbc:ID>VAT</cbc:ID>
                </cac:TaxScheme>
            </cac:TaxCategory>
        </cac:TaxSubtotal>
        <cac:TaxSubtotal>
            <cbc:TaxableAmount currencyID="RON">5442.28</cbc:TaxableAmount>
            <cbc:TaxAmount currencyID="RON">309.82</cbc:TaxAmount>
            <cac:TaxCategory>
                <cbc:ID>E</cbc:ID>
                <cbc:Percent>2.78</cbc:Percent>
                <cbc:TaxExemptionReasonCode>1153</cbc:TaxExemptionReasonCode>
                <cbc:TaxExemptionReason>redefine user-centric convergence</cbc:TaxExemptionReason>
                <cac:TaxScheme>
                    <cbc:ID>VAT</cbc:ID>
                </cac:TaxScheme>
            </cac:TaxCategory>
        </cac:TaxSubtotal>
    </cac:TaxTotal>
    <cac:TaxTotal>
        <cbc:TaxAmount currencyID="RON">309.82</cbc:TaxAmount>
    </cac:TaxTotal>
    <cac:LegalMonetaryTotal>
        <cbc:LineExtensionAmount currencyID="RON">1822.1</cbc:LineExtensionAmount>
        <cbc:TaxExclusiveAmount currencyID="RON">6087.03</cbc:TaxExclusiveAmount>
        <cbc:TaxInclusiveAmount currencyID="RON">4423.25</cbc:TaxInclusiveAmount>
        <cbc:AllowanceTotalAmount currencyID="RON">85.28</cbc:AllowanceTotalAmount>
        <cbc:ChargeTotalAmount currencyID="RON">808.38</cbc:ChargeTotalAmount>
        <cbc:PrepaidAmount currencyID="RON">4724.47</cbc:PrepaidAmount>
        <cbc:PayableRoundingAmount currencyID="RON">65.17</cbc:PayableRoundingAmount>
        <cbc:PayableAmount currencyID="RON">7830.31</cbc:PayableAmount>
    </cac:LegalMonetaryTotal>
    <cac:InvoiceLine>
        <cbc:ID>1</cbc:ID>
        <cbc:InvoicedQuantity unitCode="57">40.35</cbc:InvoicedQuantity>
        <cbc:LineExtensionAmount currencyID="RON">1822.1</cbc:LineExtensionAmount>
        <cac:Item>
            <cbc:Name>believe</cbc:Name>
            <cac:ClassifiedTaxCategory>
                <cbc:ID>E</cbc:ID>
                <cbc:Percent>0.83</cbc:Percent>
                <cac:TaxScheme>
                    <cbc:ID>VAT</cbc:ID>
                </cac:TaxScheme>
            </cac:ClassifiedTaxCategory>
        </cac:Item>
        <cac:Price>
            <cbc:PriceAmount currencyID="RON">363.88</cbc:PriceAmount>
        </cac:Price>
    </cac:InvoiceLine>
</Invoice>
<!--XML generat cu aplicatia ANAF stage Beta-->